{
  "Name": "TDM V3",
  "Description": "Team Death Match. Битва двух команд",
  "StartClientVersion": 703,
  "MapFilter": {
    "IsBlank": false,
    "HasParcourEnd": false
  },
  "MapLists": [
    {
      "MapListId": 324,
      "Name": "Официальные карты",
      "Parameters": {
        "GameLength": "Length_S"
      }
    },
    {
      "MapListId": 581,
      "Parameters": {
        "GameLength": "Length_XL"
      }
    }
  ],
  "ParametersDeclaration": [
    {
      "Name": "GameLength",
      "Type": "String",
      "Default": "Length_M"
    }
  ],
  "Parameters": {
    "Bool": [
      {
        "Name": "MapRotation",
        "DisplayName": "GmParams/MapRotation",
        "Default": true,
        "Order": 1
      },
      {
        "Name": "OnlyKnives",
        "DisplayName": "GmParams/OnlyKnives",
        "Order": 2
      },
      {
        "Name": "OnlyPlayerBlocksDmg",
        "DisplayName": "GmParams/OnlyPlayerBlocksDmg",
        "Order": 3
      },
      {
        "Name": "LoosenBlocks",
        "DisplayName": "GmParams/LoosenBlocks",
        "Order": 4
      },
      {
        "Name": "FriendlyFire",
        "DisplayName": "GmParams/FriendlyFire",
        "Order": 5
      }
    ]
  }
}